cppsage/__init__.py
cppsage/cli.py
cppsage/commands.py
cppsage-0.4.9.dist-info/METADATA
cppsage-0.4.9.dist-info/WHEEL
cppsage-0.4.9.dist-info/entry_points.txt
cppsage-0.4.9.dist-info/top_level.txt
cppsage-0.4.9.dist-info/RECORD
