Metadata-Version: 2.4
Name: cppsage
Version: 0.4.9
Summary: Sage: A Unified Project and Package Management System for C/C++ by Version6
Author-email: Vishal Ahirwar <cvxxcv0091@gmail.com>
License: MIT
Project-URL: Homepage, https://github.com/officialv6/cppsage
Requires-Python: >=3.7
Requires-Dist: typer
Requires-Dist: rich
Requires-Dist: questionary
Requires-Dist: prompt_toolkit==3.0.36
